{
  "comments": {
    "1": {
      "body": "laudantium enim quasi est quidem magnam voluptate ipsam eos tempora quo necessitatibus dolor quam autem quasi reiciendis et nam sapiente accusantium",
      "email": "Eliseo@gardner.biz",
      "name": "táo",
      "postId": 1
    },
    "2": {
      "body": "est natus enim nihil est dolore omnis voluptatem numquam et omnis occaecati quod ullam at voluptatem error expedita pariatur nihil sint nostrum voluptatem reiciendis et",
      "email": "Jayne_Kuhic@sydney.com",
      "name": "Bơ",
      "postId": 1
    },
    "3": {
      "body": "fuga eos qui dolor rerum inventore corporis exercitationem corporis cupiditate et deserunt recusandae est sed quis culpa eum maiores corporis et",
      "email": "Kariane@jadyn.tv",
      "name": "Cam",
      "postId": 2
    },
    "4": {
      "body": "Có thể nói đây là hình mẫu làm trắng da bằng trái cây, những người thường xuyên thức khuya rất dễ bị đốm và mụn trên mặt, axit citric có thể xóa mờ vết thâm và ngăn ngừa nám",
      "email": "Mariana_Orn@preston.org",
      "name": "Chanh",
      "postId": 2
    },
    "-NpENjyPp9rtEsvnG6-p": {
      "body": "This is a new comment.",
      "email": "new_comment@example.com",
      "name": "New Comment",
      "postId": 1
    },
    "-NpENkLWc8ZNdShvMV8E": {
      "body": "This is a new comment.",
      "email": "new_comment@example.com",
      "name": "New Comment",
      "postId": 1
    },
    "-NpENljwhj707sXKQRDN": {
      "body": "This is a new comment.",
      "email": "new_comment@example.com",
      "name": "New Comment",
      "postId": 1
    },
    "-NpEO33WZ7e-Hl3fy3eR": {
      "body": "This is a new comment.",
      "email": "new_comment@example.com",
      "name": "New Comment",
      "postId": 1
    }
  }
}